funcnodes_pydantic/__init__.py
funcnodes_pydantic/_demo.py
funcnodes_pydantic/models.py
funcnodes_pydantic/union_flattener.py
funcnodes_pydantic/unpackers.py
funcnodes_pydantic-1.2.0.dist-info/METADATA
funcnodes_pydantic-1.2.0.dist-info/WHEEL
funcnodes_pydantic-1.2.0.dist-info/entry_points.txt
funcnodes_pydantic-1.2.0.dist-info/licenses/LICENSE
funcnodes_pydantic-1.2.0.dist-info/RECORD
